ArtusAPI/__init__.py
ArtusAPI/artus_api.py
ArtusAPI/commands/__init__.py
ArtusAPI/commands/commands.py
ArtusAPI/communication/__init__.py
ArtusAPI/communication/communication.py
ArtusAPI/communication/UART/__init__.py
ArtusAPI/communication/UART/uart.py
ArtusAPI/communication/WiFi/__init__.py
ArtusAPI/communication/WiFi/wifi_server.py
ArtusAPI/firmware_update/__init__.py
ArtusAPI/firmware_update/firmware_updater.py
ArtusAPI/firmware_update/run_full_firmware_update.py
ArtusAPI/robot/__init__.py
ArtusAPI/robot/robot.py
ArtusAPI/robot/artus_lite/__init__.py
ArtusAPI/robot/artus_lite/artus_lite.py
ArtusAPI/robot/artus_lite/artus_lite_left.py
ArtusAPI/robot/artus_lite/artus_lite_plus.py
ArtusAPI/robot/artus_lite/artus_lite_plus_left.py
ArtusAPI/robot/artus_lite/artus_lite_plus_right.py
ArtusAPI/robot/artus_lite/artus_lite_right.py
ArtusAPI/sensors/ForceSensor.py
ArtusAPI/sensors/__init__.py
ArtusAPI-1.3.18.dist-info/METADATA
ArtusAPI-1.3.18.dist-info/WHEEL
ArtusAPI-1.3.18.dist-info/entry_points.txt
ArtusAPI-1.3.18.dist-info/top_level.txt
ArtusAPI-1.3.18.dist-info/RECORD
