Metadata-Version: 2.1
Name: ArtusAPI
Version: 1.3.18
Summary: API to control Artus Family of Robots by Sarcomere Dynamics Inc
Home-page: https://sarcomeredynamics.com/home
Author: Sarcomere Dynamics Inc.
Author-email: support@sarcomeredynamics.com
License: UNKNOWN
Project-URL: Source, https://github.com/Sarcomere-Dynamics/Sarcomere_Dynamics_Resources
Keywords: robotics,artus,sarcomere dynamics,control
Platform: UNKNOWN
Requires-Python: >=3.10
Requires-Dist: esptool
Requires-Dist: psutil (==5.9.8)
Requires-Dist: pyserial (==3.5)
Requires-Dist: pyyaml
Requires-Dist: requests
Requires-Dist: tqdm
